lightrag_mcp/__init__.py
lightrag_mcp/config.py
lightrag_mcp/lightrag_client.py
lightrag_mcp/main.py
lightrag_mcp/server.py
lightrag_mcp/client/__init__.py
lightrag_mcp/client/light_rag_server_api_client/__init__.py
lightrag_mcp/client/light_rag_server_api_client/client.py
lightrag_mcp/client/light_rag_server_api_client/errors.py
lightrag_mcp/client/light_rag_server_api_client/py.typed
lightrag_mcp/client/light_rag_server_api_client/types.py
lightrag_mcp/client/light_rag_server_api_client/api/__init__.py
lightrag_mcp/client/light_rag_server_api_client/api/default/__init__.py
lightrag_mcp/client/light_rag_server_api_client/api/default/get_auth_status_auth_status_get.py
lightrag_mcp/client/light_rag_server_api_client/api/default/get_status_health_get.py
lightrag_mcp/client/light_rag_server_api_client/api/default/login_login_post.py
lightrag_mcp/client/light_rag_server_api_client/api/default/redirect_to_webui_get.py
lightrag_mcp/client/light_rag_server_api_client/api/documents/__init__.py
lightrag_mcp/client/light_rag_server_api_client/api/documents/clear_documents_documents_delete.py
lightrag_mcp/client/light_rag_server_api_client/api/documents/documents_documents_get.py
lightrag_mcp/client/light_rag_server_api_client/api/documents/get_pipeline_status_documents_pipeline_status_get.py
lightrag_mcp/client/light_rag_server_api_client/api/documents/insert_batch_documents_file_batch_post.py
lightrag_mcp/client/light_rag_server_api_client/api/documents/insert_file_documents_file_post.py
lightrag_mcp/client/light_rag_server_api_client/api/documents/insert_text_documents_text_post.py
lightrag_mcp/client/light_rag_server_api_client/api/documents/insert_texts_documents_texts_post.py
lightrag_mcp/client/light_rag_server_api_client/api/documents/scan_for_new_documents_documents_scan_post.py
lightrag_mcp/client/light_rag_server_api_client/api/documents/upload_to_input_dir_documents_upload_post.py
lightrag_mcp/client/light_rag_server_api_client/api/graph/__init__.py
lightrag_mcp-0.1.0.dist-info/METADATA
lightrag_mcp-0.1.0.dist-info/WHEEL
lightrag_mcp-0.1.0.dist-info/entry_points.txt
lightrag_mcp-0.1.0.dist-info/RECORD
